{
  "bookId": "generative-ai-in-defence-applications-ethics-an-af931312",
  "directory": "Generative_AI_in_Defence__Applications__Ethics__an_af931312",
  "title": "Generative AI In Defence Applications Ethics An Af931312",
  "category": "Artificial Intelligence",
  "generatedAt": "2025-07-14T17:23:19.900Z",
  "summary": {
    "overallScore": 5.920886256976768,
    "readabilityGrade": "Very Poor",
    "wordCount": 32833,
    "estimatedReadingTime": 165
  },
  "readabilityMetrics": {
    "fleschScore": -30.197784357558078,
    "fleschGrade": "Graduate",
    "fleschKincaidGrade": 20.718377668105592,
    "fogIndex": 25.121584646370042,
    "smogIndex": 17.694248362691994,
    "ariIndex": 21.85565394169995,
    "cliIndex": 0,
    "avgSentenceLength": 13.070461783439491,
    "avgSyllablesPerWord": 2.6449913197088297,
    "complexWordRatio": 0.4973349983248561
  },
  "sentenceAnalysis": {
    "totalSentences": 2512,
    "avgWordsPerSentence": 20.71815286624204,
    "avgSyllablesPerWord": 2.110694796710476,
    "longSentences": 506,
    "shortSentences": 36,
    "complexWords": 16935,
    "passiveVoice": 390,
    "questions": 0,
    "exclamations": 0,
    "subordinateClauses": 664,
    "readabilityIssues": [
      "Sentences too long (avg: 20.7 words)",
      "Complex vocabulary (avg: 2.1 syllables/word)"
    ]
  },
  "vocabularyComplexity": {
    "totalWords": 32833,
    "uniqueWords": 3755,
    "vocabularyRichness": 0.1143666433161758,
    "rareWords": 709,
    "technicalTerms": 7188,
    "jargonWords": 847,
    "avgWordLength": 7.802637590229343,
    "complexityScore": 0.26631742454238116
  },
  "structurePatterns": {
    "headers": 2,
    "subheaders": 9,
    "bulletPoints": 676,
    "numberedLists": 19,
    "codeBlocks": 0,
    "quotes": 37,
    "links": 95,
    "emphasis": 201,
    "paragraphs": 790,
    "avgParagraphLength": 65.18481012658228,
    "tableOfContents": true,
    "summaries": 56,
    "examples": 62,
    "definitions": 8
  },
  "recommendations": [
    {
      "category": "Sentence Structure",
      "priority": "High",
      "issue": "Average sentence length is 20.7 words",
      "recommendation": "Break long sentences into shorter ones. Aim for 12-18 words per sentence.",
      "impact": "High - Shorter sentences significantly improve readability"
    },
    {
      "category": "Vocabulary",
      "priority": "High",
      "issue": "High vocabulary complexity score: 26.6%",
      "recommendation": "Replace technical terms with simpler alternatives where possible. Add definitions for necessary jargon.",
      "impact": "High - Simpler vocabulary makes content accessible to wider audience"
    },
    {
      "category": "Structure",
      "priority": "Medium",
      "issue": "Insufficient headers and subheaders for content length",
      "recommendation": "Add more headings to break up content. Aim for 1 header per 200-400 words.",
      "impact": "Medium - Better structure improves navigation and comprehension"
    },
    {
      "category": "Reading Flow",
      "priority": "High",
      "issue": "Very low Flesch Reading Ease score: -30.2",
      "recommendation": "Focus on shorter sentences and simpler words. Consider adding examples and analogies.",
      "impact": "High - Improving flow makes content much more accessible"
    }
  ],
  "improvementPriorities": [
    {
      "priority": "Critical",
      "score": 10,
      "item": "Shorten long sentences"
    },
    {
      "priority": "Critical",
      "score": 9,
      "item": "Simplify vocabulary"
    },
    {
      "priority": "High",
      "score": 8,
      "item": "Improve reading flow"
    },
    {
      "priority": "Medium",
      "score": 7,
      "item": "Add more structure"
    }
  ],
  "benchmarks": {
    "overallScore": {
      "bookScore": 5.920886256976768,
      "libraryAverage": 38.35,
      "comparison": "Below Average",
      "percentile": 10
    },
    "fleschScore": {
      "bookScore": -30.197784357558078,
      "libraryAverage": 20.87,
      "comparison": "Below Average"
    },
    "sentenceLength": {
      "bookScore": 13.070461783439491,
      "libraryAverage": 10.23,
      "comparison": "Worse"
    },
    "vocabularyComplexity": {
      "bookScore": 0.26631742454238116,
      "libraryAverage": 0.119,
      "comparison": "More Complex"
    }
  }
}